{"is_source_file": true, "format": "JavaScript", "description": "Entry point of the React application that renders the main App component into the DOM.", "external_files": ["./App", "./index.css"], "external_methods": ["React.StrictMode", "ReactDOM.createRoot"], "published": ["root"], "classes": [], "methods": [], "calls": ["ReactDOM.createRoot", "root.render"], "search-terms": ["React", "App", "root"], "state": 2, "file_id": 6, "knowledge_revision": 18, "git_revision": "8b39ff3516f3414564d9502fdce385dd72642dcc", "ctags": [{"_type": "tag", "name": "root", "path": "/tmp/kavia/workspace/code-generation/browser-snake-game-631800-631809/snake_game_frontend/src/index.js", "pattern": "/^const root = ReactDOM.createRoot(document.getElementById('root'));$/", "language": "JavaScript", "kind": "constant"}], "hash": "9fc5841375336fc175b49f8767a11383", "format-version": 4, "code-base-name": "snake_game_frontend", "filename": "snake_game_frontend/src/index.js", "revision_history": [{"18": "8b39ff3516f3414564d9502fdce385dd72642dcc"}]}